{
  "curriculum": {
    "classId": "string",
    "term": "string",
    "name": "string",
    "teacher": "string",
    "dayOfWeek": "int",
    "date": "date",
    "startTime": "date",
    "endTime": "date",
    "memo": "string",
    "created": "date",
    "modified": "date"
  },
  "curriculum": {
    "classId": "string",
    "term": "string|2015-1",
    "courses": [
      {
        "name": "string",
        "teacher": "string",
        "dayOfWeek": "int",
        "startTime": "date",
        "endTime": "date",
        "date": "date|optional",
        "memo": "string"
      }
    ],
    "created": "date",
    "modified": "date"
  }
}
